override/__init__.py
override/__main__.py
override/cli.py
override/logs.py
override/project.py
override/updates.py
pyoverride-0.9.2.dist-info/DESCRIPTION.rst
pyoverride-0.9.2.dist-info/METADATA
pyoverride-0.9.2.dist-info/RECORD
pyoverride-0.9.2.dist-info/WHEEL
pyoverride-0.9.2.dist-info/metadata.json
pyoverride-0.9.2.dist-info/top_level.txt
