Metadata-Version: 2.0
Name: pyoverride
Version: 0.9.2
Summary: Python project configuration
Home-page: https://github.com/davidhyman/override
Author: David Hyman
Author-email: david.hyman...@gmail.com
License: MIT
Download-URL: https://github.com/davidhyman/override/archive/0.9.tar.gz
Keywords: settings,configuration,override
Platform: UNKNOWN
Classifier: Programming Language :: Python :: 3
Requires-Python: >=3
Requires-Dist: pystache (==0.5.4)
